{
    "version": "0.3.14-fixed",
    "steps": [
        {
            "tag": "CreateField",
            "model": "User",
            "field": "hintCount",
            "type": "Int",
            "arity": "Required"
        },
        {
            "tag": "CreateDirective",
            "location": {
                "path": {
                    "tag": "Field",
                    "model": "User",
                    "field": "hintCount"
                },
                "directive": "default"
            }
        },
        {
            "tag": "CreateArgument",
            "location": {
                "tag": "Directive",
                "path": {
                    "tag": "Field",
                    "model": "User",
                    "field": "hintCount"
                },
                "directive": "default"
            },
            "argument": "",
            "value": "3"
        }
    ]
}
